LICENSE
MANIFEST.in
README.rst
aur.py
requirements.txt
setup.py
aur.egg-info/PKG-INFO
aur.egg-info/SOURCES.txt
aur.egg-info/dependency_links.txt
aur.egg-info/not-zip-safe
aur.egg-info/requires.txt
aur.egg-info/top_level.txt
tests/requirements.txt
tests/unit_tests.py
tests/samples/msearch_found.api_response
tests/samples/msearch_found.args
tests/samples/msearch_found.expected
tests/samples/msearch_not_found.api_response
tests/samples/msearch_not_found.args
tests/samples/msearch_not_found.expected
tests/samples/multiinfo_found.api_response
tests/samples/multiinfo_found.args
tests/samples/multiinfo_found.expected
tests/samples/multiinfo_not_found.api_response
tests/samples/multiinfo_not_found.args
tests/samples/multiinfo_not_found.expected
tests/samples/multiinfo_only_partial_found.api_response
tests/samples/multiinfo_only_partial_found.args
tests/samples/multiinfo_only_partial_found.expected
tests/samples/search_found.api_response
tests/samples/search_found.args
tests/samples/search_found.expected
tests/samples/search_not_found.api_response
tests/samples/search_not_found.args
tests/samples/search_not_found.expected