Metadata-Version: 1.1
Name: aur
Version: 0.10.0
Summary: Arch User Repository API interface.
Home-page: https://github.com/cdown/aur
Author: Chris Down
Author-email: chris@chrisdown.name
License: ISC
Keywords: aur arch linux
Platform: UNKNOWN
Classifier: Development Status :: 2 - Pre-Alpha
Classifier: License :: OSI Approved :: ISC License (ISCL)
Classifier: Programming Language :: Python :: 2
Classifier: Programming Language :: Python :: 2.7
Classifier: Programming Language :: Python :: 3
Classifier: Programming Language :: Python :: 3.3
Classifier: Programming Language :: Python :: 3.4
